cantata/__init__.py
cantata/main.py
cantata/templates/cantata.c.cogen
cantata/templates/cantata.h.cogen
python_cantata-1.3.1.dist-info/License.txt
python_cantata-1.3.1.dist-info/METADATA
python_cantata-1.3.1.dist-info/WHEEL
python_cantata-1.3.1.dist-info/top_level.txt
python_cantata-1.3.1.dist-info/RECORD
