Metadata-Version: 2.1
Name: python-cantata
Version: 1.3.1
Summary: Python Tool to generate C structures and functions to access candb information
Home-page: https://github.com/polfeliu/cantata
Author: Pol Feliu Cuberes
Author-email: feliupol@gmail.com
License: UNKNOWN
Project-URL: Source, https://github.com/polfeliu/cantata
Keywords: sample setuptools development
Platform: UNKNOWN
Requires-Python: >=3
Requires-Dist: aenum (==3.0.0)
Requires-Dist: bitstruct (==8.11.1)
Requires-Dist: cantools (==36.2.0)
Requires-Dist: cogapp (==3.0.0)
Requires-Dist: cycler (==0.10.0)
Requires-Dist: matplotlib (==3.3.4)
Requires-Dist: textparser (==0.23.0)
Requires-Dist: windows-curses (==2.2.0)
Requires-Dist: wrapt (==1.12.1)
Requires-Dist: pyparsing (==2.4.7) ; python_version >= "2.6" and python_version not in "3.0, 3.1, 3.2"
Requires-Dist: python-can (==3.3.4) ; python_version >= "2.7"
Requires-Dist: python-dateutil (==2.8.1) ; python_version >= "2.7" and python_version not in "3.0, 3.1, 3.2"
Requires-Dist: six (==1.15.0) ; python_version >= "2.7" and python_version not in "3.0, 3.1, 3.2"
Requires-Dist: diskcache (==5.2.1) ; python_version >= "3"
Requires-Dist: argparse-addons (==0.7.0) ; python_version >= "3.6"
Requires-Dist: kiwisolver (==1.3.1) ; python_version >= "3.6"
Requires-Dist: pillow (==8.1.0) ; python_version >= "3.6"
Requires-Dist: numpy (==1.20.1) ; python_version >= "3.7"
